[
  {
    "model": "debtcalculatorapp.currency",
    "pk": 1,
    "fields": {
      "full_name": "United Arab Emirates Dirham",
      "code": "AED"
    }
  },
  {
    "model": "debtcalculatorapp.currency",
    "pk": 2,
    "fields": {
      "full_name": "Afghanistan Afghani",
      "code": "AFN"
    }
  },
  {
    "model": "debtcalculatorapp.currency",
    "pk": 3,
    "fields": {
      "full_name": "Albania Lek",
      "code": "ALL"
    }
  },
  {
    "model": "debtcalculatorapp.currency",
    "pk": 4,
    "fields": {
      "full_name": "Armenia Dram",
      "code": "AMD"
    }
  },
  {
    "model": "debtcalculatorapp.currency",
    "pk": 5,
    "fields": {
      "full_name": "Netherlands Antilles Guilder",
      "code": "ANG"
    }
  },
  {
    "model": "debtcalculatorapp.currency",
    "pk": 6,
    "fields": {
      "full_name": "Angola Kwanza",
      "code": "AOA"
    }
  },
  {
    "model": "debtcalculatorapp.currency",
    "pk": 7,
    "fields": {
      "full_name": "Argentina Peso",
      "code": "ARS"
    }
  },
  {
    "model": "debtcalculatorapp.currency",
    "pk": 8,
    "fields": {
      "full_name": "Australia Dollar",
      "code": "AUD"
    }
  },
  {
    "model": "debtcalculatorapp.currency",
    "pk": 9,
    "fields": {
      "full_name": "Aruba Guilder",
      "code": "AWG"
    }
  },
  {
    "model": "debtcalculatorapp.currency",
    "pk": 10,
    "fields": {
      "full_name": "Azerbaijan Manat",
      "code": "AZN"
    }
  },
  {
    "model": "debtcalculatorapp.currency",
    "pk": 11,
    "fields": {
      "full_name": "Bosnia & Herzegovina Convertible Marka",
      "code": "BAM"
    }
  },
  {
    "model": "debtcalculatorapp.currency",
    "pk": 12,
    "fields": {
      "full_name": "Barbados Dollar",
      "code": "BBD"
    }
  },
  {
    "model": "debtcalculatorapp.currency",
    "pk": 13,
    "fields": {
      "full_name": "Bangladesh Taka",
      "code": "BDT"
    }
  },
  {
    "model": "debtcalculatorapp.currency",
    "pk": 14,
    "fields": {
      "full_name": "Bulgaria Lev",
      "code": "BGN"
    }
  },
  {
    "model": "debtcalculatorapp.currency",
    "pk": 15,
    "fields": {
      "full_name": "Bahrain Dinar",
      "code": "BHD"
    }
  },
  {
    "model": "debtcalculatorapp.currency",
    "pk": 16,
    "fields": {
      "full_name": "Burundi Franc",
      "code": "BIF"
    }
  },
  {
    "model": "debtcalculatorapp.currency",
    "pk": 17,
    "fields": {
      "full_name": "Bermuda Dollar",
      "code": "BMD"
    }
  },
  {
    "model": "debtcalculatorapp.currency",
    "pk": 18,
    "fields": {
      "full_name": "Brunei Darussalam Dollar",
      "code": "BND"
    }
  },
  {
    "model": "debtcalculatorapp.currency",
    "pk": 19,
    "fields": {
      "full_name": "Bolivia Bolíviano",
      "code": "BOB"
    }
  },
  {
    "model": "debtcalculatorapp.currency",
    "pk": 20,
    "fields": {
      "full_name": "Brazil Real",
      "code": "BRL"
    }
  },
  {
    "model": "debtcalculatorapp.currency",
    "pk": 21,
    "fields": {
      "full_name": "Bahamas Dollar",
      "code": "BSD"
    }
  },
  {
    "model": "debtcalculatorapp.currency",
    "pk": 22,
    "fields": {
      "full_name": "Bhutan Ngultrum",
      "code": "BTN"
    }
  },
  {
    "model": "debtcalculatorapp.currency",
    "pk": 23,
    "fields": {
      "full_name": "Botswana Pula",
      "code": "BWP"
    }
  },
  {
    "model": "debtcalculatorapp.currency",
    "pk": 24,
    "fields": {
      "full_name": "Belarus Ruble",
      "code": "BYN"
    }
  },
  {
    "model": "debtcalculatorapp.currency",
    "pk": 25,
    "fields": {
      "full_name": "Belize Dollar",
      "code": "BZD"
    }
  },
  {
    "model": "debtcalculatorapp.currency",
    "pk": 26,
    "fields": {
      "full_name": "Canada Dollar",
      "code": "CAD"
    }
  },
  {
    "model": "debtcalculatorapp.currency",
    "pk": 27,
    "fields": {
      "full_name": "Congo/Kinshasa Franc",
      "code": "CDF"
    }
  },
  {
    "model": "debtcalculatorapp.currency",
    "pk": 28,
    "fields": {
      "full_name": "Switzerland Franc",
      "code": "CHF"
    }
  },
  {
    "model": "debtcalculatorapp.currency",
    "pk": 29,
    "fields": {
      "full_name": "Chile Peso",
      "code": "CLP"
    }
  },
  {
    "model": "debtcalculatorapp.currency",
    "pk": 30,
    "fields": {
      "full_name": "China Yuan Renminbi",
      "code": "CNY"
    }
  },
  {
    "model": "debtcalculatorapp.currency",
    "pk": 31,
    "fields": {
      "full_name": "Colombia Peso",
      "code": "COP"
    }
  },
  {
    "model": "debtcalculatorapp.currency",
    "pk": 32,
    "fields": {
      "full_name": "Costa Rica Colon",
      "code": "CRC"
    }
  },
  {
    "model": "debtcalculatorapp.currency",
    "pk": 33,
    "fields": {
      "full_name": "Cuba Convertible Peso",
      "code": "CUC"
    }
  },
  {
    "model": "debtcalculatorapp.currency",
    "pk": 34,
    "fields": {
      "full_name": "Cuba Peso",
      "code": "CUP"
    }
  },
  {
    "model": "debtcalculatorapp.currency",
    "pk": 35,
    "fields": {
      "full_name": "Cape Verde Escudo",
      "code": "CVE"
    }
  },
  {
    "model": "debtcalculatorapp.currency",
    "pk": 36,
    "fields": {
      "full_name": "Czech Republic Koruna",
      "code": "CZK"
    }
  },
  {
    "model": "debtcalculatorapp.currency",
    "pk": 37,
    "fields": {
      "full_name": "Djibouti Franc",
      "code": "DJF"
    }
  },
  {
    "model": "debtcalculatorapp.currency",
    "pk": 38,
    "fields": {
      "full_name": "Denmark Krone",
      "code": "DKK"
    }
  },
  {
    "model": "debtcalculatorapp.currency",
    "pk": 39,
    "fields": {
      "full_name": "Dominican Republic Peso",
      "code": "DOP"
    }
  },
  {
    "model": "debtcalculatorapp.currency",
    "pk": 40,
    "fields": {
      "full_name": "Algeria Dinar",
      "code": "DZD"
    }
  },
  {
    "model": "debtcalculatorapp.currency",
    "pk": 41,
    "fields": {
      "full_name": "Egypt Pound",
      "code": "EGP"
    }
  },
  {
    "model": "debtcalculatorapp.currency",
    "pk": 42,
    "fields": {
      "full_name": "Eritrea Nakfa",
      "code": "ERN"
    }
  },
  {
    "model": "debtcalculatorapp.currency",
    "pk": 43,
    "fields": {
      "full_name": "Ethiopia Birr",
      "code": "ETB"
    }
  },
  {
    "model": "debtcalculatorapp.currency",
    "pk": 44,
    "fields": {
      "full_name": "Euro Member Countries",
      "code": "EUR"
    }
  },
  {
    "model": "debtcalculatorapp.currency",
    "pk": 45,
    "fields": {
      "full_name": "Fiji Dollar",
      "code": "FJD"
    }
  },
  {
    "model": "debtcalculatorapp.currency",
    "pk": 46,
    "fields": {
      "full_name": "Falkland Islands Pound",
      "code": "FKP"
    }
  },
  {
    "model": "debtcalculatorapp.currency",
    "pk": 47,
    "fields": {
      "full_name": "United Kingdom Pound",
      "code": "GBP"
    }
  },
  {
    "model": "debtcalculatorapp.currency",
    "pk": 48,
    "fields": {
      "full_name": "Georgia Lari",
      "code": "GEL"
    }
  },
  {
    "model": "debtcalculatorapp.currency",
    "pk": 49,
    "fields": {
      "full_name": "Guernsey Pound",
      "code": "GGP"
    }
  },
  {
    "model": "debtcalculatorapp.currency",
    "pk": 50,
    "fields": {
      "full_name": "Ghana Cedi",
      "code": "GHS"
    }
  },
  {
    "model": "debtcalculatorapp.currency",
    "pk": 51,
    "fields": {
      "full_name": "Gibraltar Pound",
      "code": "GIP"
    }
  },
  {
    "model": "debtcalculatorapp.currency",
    "pk": 52,
    "fields": {
      "full_name": "Gambia Dalasi",
      "code": "GMD"
    }
  },
  {
    "model": "debtcalculatorapp.currency",
    "pk": 53,
    "fields": {
      "full_name": "Guinea Franc",
      "code": "GNF"
    }
  },
  {
    "model": "debtcalculatorapp.currency",
    "pk": 54,
    "fields": {
      "full_name": "Guatemala Quetzal",
      "code": "GTQ"
    }
  },
  {
    "model": "debtcalculatorapp.currency",
    "pk": 55,
    "fields": {
      "full_name": "Guyana Dollar",
      "code": "GYD"
    }
  },
  {
    "model": "debtcalculatorapp.currency",
    "pk": 56,
    "fields": {
      "full_name": "Hong Kong Dollar",
      "code": "HKD"
    }
  },
  {
    "model": "debtcalculatorapp.currency",
    "pk": 57,
    "fields": {
      "full_name": "Honduras Lempira",
      "code": "HNL"
    }
  },
  {
    "model": "debtcalculatorapp.currency",
    "pk": 58,
    "fields": {
      "full_name": "Croatia Kuna",
      "code": "HRK"
    }
  },
  {
    "model": "debtcalculatorapp.currency",
    "pk": 59,
    "fields": {
      "full_name": "Haiti Gourde",
      "code": "HTG"
    }
  },
  {
    "model": "debtcalculatorapp.currency",
    "pk": 60,
    "fields": {
      "full_name": "Hungary Forint",
      "code": "HUF"
    }
  },
  {
    "model": "debtcalculatorapp.currency",
    "pk": 61,
    "fields": {
      "full_name": "Indonesia Rupiah",
      "code": "IDR"
    }
  },
  {
    "model": "debtcalculatorapp.currency",
    "pk": 62,
    "fields": {
      "full_name": "Israel Shekel",
      "code": "ILS"
    }
  },
  {
    "model": "debtcalculatorapp.currency",
    "pk": 63,
    "fields": {
      "full_name": "Isle of Man Pound",
      "code": "IMP"
    }
  },
  {
    "model": "debtcalculatorapp.currency",
    "pk": 64,
    "fields": {
      "full_name": "India Rupee",
      "code": "INR"
    }
  },
  {
    "model": "debtcalculatorapp.currency",
    "pk": 65,
    "fields": {
      "full_name": "Iraq Dinar",
      "code": "IQD"
    }
  },
  {
    "model": "debtcalculatorapp.currency",
    "pk": 66,
    "fields": {
      "full_name": "Iran Rial",
      "code": "IRR"
    }
  },
  {
    "model": "debtcalculatorapp.currency",
    "pk": 67,
    "fields": {
      "full_name": "Iceland Krona",
      "code": "ISK"
    }
  },
  {
    "model": "debtcalculatorapp.currency",
    "pk": 68,
    "fields": {
      "full_name": "Jersey Pound",
      "code": "JEP"
    }
  },
  {
    "model": "debtcalculatorapp.currency",
    "pk": 69,
    "fields": {
      "full_name": "Jamaica Dollar",
      "code": "JMD"
    }
  },
  {
    "model": "debtcalculatorapp.currency",
    "pk": 70,
    "fields": {
      "full_name": "Jordan Dinar",
      "code": "JOD"
    }
  },
  {
    "model": "debtcalculatorapp.currency",
    "pk": 71,
    "fields": {
      "full_name": "Japan Yen",
      "code": "JPY"
    }
  },
  {
    "model": "debtcalculatorapp.currency",
    "pk": 72,
    "fields": {
      "full_name": "Kenya Shilling",
      "code": "KES"
    }
  },
  {
    "model": "debtcalculatorapp.currency",
    "pk": 73,
    "fields": {
      "full_name": "Kyrgyzstan Som",
      "code": "KGS"
    }
  },
  {
    "model": "debtcalculatorapp.currency",
    "pk": 74,
    "fields": {
      "full_name": "Cambodia Riel",
      "code": "KHR"
    }
  },
  {
    "model": "debtcalculatorapp.currency",
    "pk": 75,
    "fields": {
      "full_name": "Comorian Franc",
      "code": "KMF"
    }
  },
  {
    "model": "debtcalculatorapp.currency",
    "pk": 76,
    "fields": {
      "full_name": "Korea (North) Won",
      "code": "KPW"
    }
  },
  {
    "model": "debtcalculatorapp.currency",
    "pk": 77,
    "fields": {
      "full_name": "Korea (South) Won",
      "code": "KRW"
    }
  },
  {
    "model": "debtcalculatorapp.currency",
    "pk": 78,
    "fields": {
      "full_name": "Kuwait Dinar",
      "code": "KWD"
    }
  },
  {
    "model": "debtcalculatorapp.currency",
    "pk": 79,
    "fields": {
      "full_name": "Cayman Islands Dollar",
      "code": "KYD"
    }
  },
  {
    "model": "debtcalculatorapp.currency",
    "pk": 80,
    "fields": {
      "full_name": "Kazakhstan Tenge",
      "code": "KZT"
    }
  },
  {
    "model": "debtcalculatorapp.currency",
    "pk": 81,
    "fields": {
      "full_name": "Laos Kip",
      "code": "LAK"
    }
  },
  {
    "model": "debtcalculatorapp.currency",
    "pk": 82,
    "fields": {
      "full_name": "Lebanon Pound",
      "code": "LBP"
    }
  },
  {
    "model": "debtcalculatorapp.currency",
    "pk": 83,
    "fields": {
      "full_name": "Sri Lanka Rupee",
      "code": "LKR"
    }
  },
  {
    "model": "debtcalculatorapp.currency",
    "pk": 84,
    "fields": {
      "full_name": "Liberia Dollar",
      "code": "LRD"
    }
  },
  {
    "model": "debtcalculatorapp.currency",
    "pk": 85,
    "fields": {
      "full_name": "Lesotho Loti",
      "code": "LSL"
    }
  },
  {
    "model": "debtcalculatorapp.currency",
    "pk": 86,
    "fields": {
      "full_name": "Libya Dinar",
      "code": "LYD"
    }
  },
  {
    "model": "debtcalculatorapp.currency",
    "pk": 87,
    "fields": {
      "full_name": "Morocco Dirham",
      "code": "MAD"
    }
  },
  {
    "model": "debtcalculatorapp.currency",
    "pk": 88,
    "fields": {
      "full_name": "Moldova Leu",
      "code": "MDL"
    }
  },
  {
    "model": "debtcalculatorapp.currency",
    "pk": 89,
    "fields": {
      "full_name": "Madagascar Ariary",
      "code": "MGA"
    }
  },
  {
    "model": "debtcalculatorapp.currency",
    "pk": 90,
    "fields": {
      "full_name": "Macedonia Denar",
      "code": "MKD"
    }
  },
  {
    "model": "debtcalculatorapp.currency",
    "pk": 91,
    "fields": {
      "full_name": "Myanmar (Burma) Kyat",
      "code": "MMK"
    }
  },
  {
    "model": "debtcalculatorapp.currency",
    "pk": 92,
    "fields": {
      "full_name": "Mongolia Tughrik",
      "code": "MNT"
    }
  },
  {
    "model": "debtcalculatorapp.currency",
    "pk": 93,
    "fields": {
      "full_name": "Macau Pataca",
      "code": "MOP"
    }
  },
  {
    "model": "debtcalculatorapp.currency",
    "pk": 94,
    "fields": {
      "full_name": "Mauritania Ouguiya",
      "code": "MRU"
    }
  },
  {
    "model": "debtcalculatorapp.currency",
    "pk": 95,
    "fields": {
      "full_name": "Mauritius Rupee",
      "code": "MUR"
    }
  },
  {
    "model": "debtcalculatorapp.currency",
    "pk": 96,
    "fields": {
      "full_name": "Maldives Rufiyaa",
      "code": "MVR"
    }
  },
  {
    "model": "debtcalculatorapp.currency",
    "pk": 97,
    "fields": {
      "full_name": "Malawi Kwacha",
      "code": "MWK"
    }
  },
  {
    "model": "debtcalculatorapp.currency",
    "pk": 98,
    "fields": {
      "full_name": "Mexico Peso",
      "code": "MXN"
    }
  },
  {
    "model": "debtcalculatorapp.currency",
    "pk": 99,
    "fields": {
      "full_name": "Malaysia Ringgit",
      "code": "MYR"
    }
  },
  {
    "model": "debtcalculatorapp.currency",
    "pk": 100,
    "fields": {
      "full_name": "Mozambique Metical",
      "code": "MZN"
    }
  },
  {
    "model": "debtcalculatorapp.currency",
    "pk": 101,
    "fields": {
      "full_name": "Namibia Dollar",
      "code": "NAD"
    }
  },
  {
    "model": "debtcalculatorapp.currency",
    "pk": 102,
    "fields": {
      "full_name": "Nigeria Naira",
      "code": "NGN"
    }
  },
  {
    "model": "debtcalculatorapp.currency",
    "pk": 103,
    "fields": {
      "full_name": "Nicaragua Cordoba",
      "code": "NIO"
    }
  },
  {
    "model": "debtcalculatorapp.currency",
    "pk": 104,
    "fields": {
      "full_name": "Norway Krone",
      "code": "NOK"
    }
  },
  {
    "model": "debtcalculatorapp.currency",
    "pk": 105,
    "fields": {
      "full_name": "Nepal Rupee",
      "code": "NPR"
    }
  },
  {
    "model": "debtcalculatorapp.currency",
    "pk": 106,
    "fields": {
      "full_name": "New Zealand Dollar",
      "code": "NZD"
    }
  },
  {
    "model": "debtcalculatorapp.currency",
    "pk": 107,
    "fields": {
      "full_name": "Oman Rial",
      "code": "OMR"
    }
  },
  {
    "model": "debtcalculatorapp.currency",
    "pk": 108,
    "fields": {
      "full_name": "Panama Balboa",
      "code": "PAB"
    }
  },
  {
    "model": "debtcalculatorapp.currency",
    "pk": 109,
    "fields": {
      "full_name": "Peru Sol",
      "code": "PEN"
    }
  },
  {
    "model": "debtcalculatorapp.currency",
    "pk": 110,
    "fields": {
      "full_name": "Papua New Guinea Kina",
      "code": "PGK"
    }
  },
  {
    "model": "debtcalculatorapp.currency",
    "pk": 111,
    "fields": {
      "full_name": "Philippines Peso",
      "code": "PHP"
    }
  },
  {
    "model": "debtcalculatorapp.currency",
    "pk": 112,
    "fields": {
      "full_name": "Pakistan Rupee",
      "code": "PKR"
    }
  },
  {
    "model": "debtcalculatorapp.currency",
    "pk": 113,
    "fields": {
      "full_name": "Poland Zloty",
      "code": "PLN"
    }
  },
  {
    "model": "debtcalculatorapp.currency",
    "pk": 114,
    "fields": {
      "full_name": "Paraguay Guarani",
      "code": "PYG"
    }
  },
  {
    "model": "debtcalculatorapp.currency",
    "pk": 115,
    "fields": {
      "full_name": "Qatar Riyal",
      "code": "QAR"
    }
  },
  {
    "model": "debtcalculatorapp.currency",
    "pk": 116,
    "fields": {
      "full_name": "Romania Leu",
      "code": "RON"
    }
  },
  {
    "model": "debtcalculatorapp.currency",
    "pk": 117,
    "fields": {
      "full_name": "Serbia Dinar",
      "code": "RSD"
    }
  },
  {
    "model": "debtcalculatorapp.currency",
    "pk": 118,
    "fields": {
      "full_name": "Russia Ruble",
      "code": "RUB"
    }
  },
  {
    "model": "debtcalculatorapp.currency",
    "pk": 119,
    "fields": {
      "full_name": "Rwanda Franc",
      "code": "RWF"
    }
  },
  {
    "model": "debtcalculatorapp.currency",
    "pk": 120,
    "fields": {
      "full_name": "Saudi Arabia Riyal",
      "code": "SAR"
    }
  },
  {
    "model": "debtcalculatorapp.currency",
    "pk": 121,
    "fields": {
      "full_name": "Solomon Islands Dollar",
      "code": "SBD"
    }
  },
  {
    "model": "debtcalculatorapp.currency",
    "pk": 122,
    "fields": {
      "full_name": "Seychelles Rupee",
      "code": "SCR"
    }
  },
  {
    "model": "debtcalculatorapp.currency",
    "pk": 123,
    "fields": {
      "full_name": "Sudan Pound",
      "code": "SDG"
    }
  },
  {
    "model": "debtcalculatorapp.currency",
    "pk": 124,
    "fields": {
      "full_name": "Sweden Krona",
      "code": "SEK"
    }
  },
  {
    "model": "debtcalculatorapp.currency",
    "pk": 125,
    "fields": {
      "full_name": "Singapore Dollar",
      "code": "SGD"
    }
  },
  {
    "model": "debtcalculatorapp.currency",
    "pk": 126,
    "fields": {
      "full_name": "Saint Helena Pound",
      "code": "SHP"
    }
  },
  {
    "model": "debtcalculatorapp.currency",
    "pk": 127,
    "fields": {
      "full_name": "Sierra Leone Leone",
      "code": "SLL"
    }
  },
  {
    "model": "debtcalculatorapp.currency",
    "pk": 128,
    "fields": {
      "full_name": "Somalia Shilling",
      "code": "SOS"
    }
  },
  {
    "model": "debtcalculatorapp.currency",
    "pk": 129,
    "fields": {
      "full_name": "Seborga Luigino",
      "code": "SPL"
    }
  },
  {
    "model": "debtcalculatorapp.currency",
    "pk": 130,
    "fields": {
      "full_name": "Surifull_name Dollar",
      "code": "SRD"
    }
  },
  {
    "model": "debtcalculatorapp.currency",
    "pk": 131,
    "fields": {
      "full_name": "São Tomé & Príncipe Dobra",
      "code": "STN"
    }
  },
  {
    "model": "debtcalculatorapp.currency",
    "pk": 132,
    "fields": {
      "full_name": "El Salvador Colon",
      "code": "SVC"
    }
  },
  {
    "model": "debtcalculatorapp.currency",
    "pk": 133,
    "fields": {
      "full_name": "Syria Pound",
      "code": "SYP"
    }
  },
  {
    "model": "debtcalculatorapp.currency",
    "pk": 134,
    "fields": {
      "full_name": "eSwatini Lilangeni",
      "code": "SZL"
    }
  },
  {
    "model": "debtcalculatorapp.currency",
    "pk": 135,
    "fields": {
      "full_name": "Thailand Baht",
      "code": "THB"
    }
  },
  {
    "model": "debtcalculatorapp.currency",
    "pk": 136,
    "fields": {
      "full_name": "Tajikistan Somoni",
      "code": "TJS"
    }
  },
  {
    "model": "debtcalculatorapp.currency",
    "pk": 137,
    "fields": {
      "full_name": "Turkmenistan Manat",
      "code": "TMT"
    }
  },
  {
    "model": "debtcalculatorapp.currency",
    "pk": 138,
    "fields": {
      "full_name": "Tunisia Dinar",
      "code": "TND"
    }
  },
  {
    "model": "debtcalculatorapp.currency",
    "pk": 139,
    "fields": {
      "full_name": "Tonga Pa'anga",
      "code": "TOP"
    }
  },
  {
    "model": "debtcalculatorapp.currency",
    "pk": 140,
    "fields": {
      "full_name": "Turkey Lira",
      "code": "TRY"
    }
  },
  {
    "model": "debtcalculatorapp.currency",
    "pk": 141,
    "fields": {
      "full_name": "Trinidad & Tobago Dollar",
      "code": "TTD"
    }
  },
  {
    "model": "debtcalculatorapp.currency",
    "pk": 142,
    "fields": {
      "full_name": "Tuvalu Dollar",
      "code": "TVD"
    }
  },
  {
    "model": "debtcalculatorapp.currency",
    "pk": 143,
    "fields": {
      "full_name": "Taiwan New Dollar",
      "code": "TWD"
    }
  },
  {
    "model": "debtcalculatorapp.currency",
    "pk": 144,
    "fields": {
      "full_name": "Tanzania Shilling",
      "code": "TZS"
    }
  },
  {
    "model": "debtcalculatorapp.currency",
    "pk": 145,
    "fields": {
      "full_name": "Ukraine Hryvnia",
      "code": "UAH"
    }
  },
  {
    "model": "debtcalculatorapp.currency",
    "pk": 146,
    "fields": {
      "full_name": "Uganda Shilling",
      "code": "UGX"
    }
  },
  {
    "model": "debtcalculatorapp.currency",
    "pk": 147,
    "fields": {
      "full_name": "United States Dollar",
      "code": "USD"
    }
  },
  {
    "model": "debtcalculatorapp.currency",
    "pk": 148,
    "fields": {
      "full_name": "Uruguay Peso",
      "code": "UYU"
    }
  },
  {
    "model": "debtcalculatorapp.currency",
    "pk": 149,
    "fields": {
      "full_name": "Uzbekistan Som",
      "code": "UZS"
    }
  },
  {
    "model": "debtcalculatorapp.currency",
    "pk": 150,
    "fields": {
      "full_name": "Venezuela Bolívar",
      "code": "VEF"
    }
  },
  {
    "model": "debtcalculatorapp.currency",
    "pk": 151,
    "fields": {
      "full_name": "Viet Nam Dong ",
      "code": "VND"
    }
  },
  {
    "model": "debtcalculatorapp.currency",
    "pk": 152,
    "fields": {
      "full_name": "Vanuatu Vatu",
      "code": "VUV"
    }
  },
  {
    "model": "debtcalculatorapp.currency",
    "pk": 153,
    "fields": {
      "full_name": "Samoa Tala",
      "code": "WST"
    }
  },
  {
    "model": "debtcalculatorapp.currency",
    "pk": 154,
    "fields": {
      "full_name": "BEAC CFA Franc",
      "code": "XAF"
    }
  },
  {
    "model": "debtcalculatorapp.currency",
    "pk": 155,
    "fields": {
      "full_name": "East Caribbean Dollar",
      "code": "XCD"
    }
  },
  {
    "model": "debtcalculatorapp.currency",
    "pk": 156,
    "fields": {
      "full_name": "IMF Special Drawing Rights",
      "code": "XDR"
    }
  },
  {
    "model": "debtcalculatorapp.currency",
    "pk": 157,
    "fields": {
      "full_name": "BCEAO Franc",
      "code": "XOF"
    }
  },
  {
    "model": "debtcalculatorapp.currency",
    "pk": 158,
    "fields": {
      "full_name": "CFP Franc",
      "code": "XPF"
    }
  },
  {
    "model": "debtcalculatorapp.currency",
    "pk": 159,
    "fields": {
      "full_name": "Yemen Rial",
      "code": "YER"
    }
  },
  {
    "model": "debtcalculatorapp.currency",
    "pk": 160,
    "fields": {
      "full_name": "South Africa Rand",
      "code": "ZAR"
    }
  },
  {
    "model": "debtcalculatorapp.currency",
    "pk": 161,
    "fields": {
      "full_name": "Zambia Kwacha",
      "code": "ZMW"
    }
  },
  {
    "model": "debtcalculatorapp.currency",
    "pk": 162,
    "fields": {
      "full_name": "Zimbabwe Dollar",
      "code": "ZWD"
    }
  }
]
